[{"file_name": "721131", "size": 1913}, {"file_name": "978538", "size": 0}, {"file_name": "873576", "size": 0}, {"file_name": "664257", "size": 0}, {"file_name": "753098", "size": 1331}][{"file_name": "721131", "size": 1913}, {"file_name": "978538", "size": 0}, {"file_name": "873576", "size": 0}, {"file_name": "664257", "size": 0}, {"file_name": "753098", "size": 1331}][{"file_name": "721131", "size": 1913}, {"file_name": "978538", "size": 0}, {"file_name": "873576", "size": 0}, {"file_name": "664257", "size": 0}, {"file_name": "753098", "size": 1331}][{"file_name": "721131", "size": 1913}, {"file_name": "978538", "size": 0}, {"file_name": "873576", "size": 0}, {"file_name": "664257", "size": 0}, {"file_name": "753098", "size": 1331}][{"file_name": "721131", "size": 1913}, {"file_name": "978538", "size": 0}, {"file_name": "873576", "size": 0}, {"file_name": "664257", "size": 0}, {"file_name": "753098", "size": 1331}][{"file_name": "721131", "size": 1913}, {"file_name": "978538", "size": 0}, {"file_name": "873576", "size": 0}, {"file_name": "664257", "size": 0}, {"file_name": "753098", "size": 1331}][{"file_name": "721131", "size": 1913}, {"file_name": "978538", "size": 0}, {"file_name": "873576", "size": 0}, {"file_name": "664257", "size": 0}, {"file_name": "753098", "size": 1331}][{"file_name": "721131", "size": 1913}, {"file_name": "978538", "size": 0}, {"file_name": "873576", "size": 0}, {"file_name": "664257", "size": 0}, {"file_name": "753098", "size": 1331}][{"file_name": "721131", "size": 1913}, {"file_name": "978538", "size": 0}, {"file_name": "873576", "size": 0}, {"file_name": "664257", "size": 0}, {"file_name": "753098", "size": 1331}][{"file_name": "721131", "size": 1913}, {"file_name": "978538", "size": 0}, {"file_name": "873576", "size": 0}, {"file_name": "664257", "size": 0}, {"file_name": "753098", "size": 1331}][{"file_name": "721131", "size": 1913}, {"file_name": "978538", "size": 0}, {"file_name": "873576", "size": 0}, {"file_name": "664257", "size": 0}, {"file_name": "753098", "size": 1331}][{"file_name": "721131", "size": 1913}, {"file_name": "978538", "size": 0}, {"file_name": "873576", "size": 0}, {"file_name": "664257", "size": 0}, {"file_name": "753098", "size": 1331}][{"file_name": "721131", "size": 1913}, {"file_name": "978538", "size": 0}, {"file_name": "873576", "size": 0}, {"file_name": "664257", "size": 0}, {"file_name": "753098", "size": 1331}][{"file_name": "721130", "size": 1913}, {"file_name": "978537", "size": 0}, {"file_name": "873575", "size": 0}, {"file_name": "664257", "size": 0}, {"file_name": "753097", "size": 1331}][{"file_name": "721130", "size": 1913}, {"file_name": "978537", "size": 0}, {"file_name": "873575", "size": 0}, {"file_name": "664257", "size": 0}, {"file_name": "753097", "size": 1331}][{"file_name": "721130", "size": 1913}, {"file_name": "978537", "size": 0}][{"file_name": "721130", "size": 1913}, {"file_name": "978537", "size": 0}, {"file_name": "873575", "size": 0}, {"file_name": "664257", "size": 0}, {"file_name": "753097", "size": 1331}][{"file_name": "17", "size": 0}][{"file_name": "17", "size": 0}][{"file_name": "74", "size": 453}, {"file_name": "48", "size": 340}, {"file_name": "24", "size": 864}, {"file_name": "67", "size": 640}, {"file_name": "96", "size": 1280}][{"file_name": "74", "size": 453}, {"file_name": "48", "size": 340}, {"file_name": "24", "size": 864}, {"file_name": "67", "size": 640}, {"file_name": "96", "size": 1280}, {"file_name": "66", "size": 853}][{"file_name": "17", "size": 0}]